quantkit/cli.py
quantkit/convert.py
quantkit/convert_exl2.py
quantkit/convert_hf.py
quantkit/quantkit.py
quantkit/safetensor.py
llm_quantkit-0.29.dist-info/LICENSE
llm_quantkit-0.29.dist-info/METADATA
llm_quantkit-0.29.dist-info/WHEEL
llm_quantkit-0.29.dist-info/entry_points.txt
llm_quantkit-0.29.dist-info/top_level.txt
llm_quantkit-0.29.dist-info/RECORD
