Metadata-Version: 2.1
Name: llm-quantkit
Version: 0.29
Summary: cli tool for downloading and quantizing LLMs
Author-email: xhedit <jevd@protonmail.com>
License: MIT License
Project-URL: repository, https://github.com/xhedit/quantkit
License-File: LICENSE
Requires-Dist: click
Requires-Dist: torch >=2.0.0
Requires-Dist: einops
Requires-Dist: tqdm
Requires-Dist: transformers
Requires-Dist: huggingface-hub
Requires-Dist: safetensors
Requires-Dist: exllamav2
Requires-Dist: llama-cpp-conv
Requires-Dist: sentencepiece
Requires-Dist: hqq
Provides-Extra: cuda
Requires-Dist: auto-gptq ; extra == 'cuda'
Requires-Dist: autoawq ; extra == 'cuda'
